tinker.sv
module instruction_decoder (
    // Instruction
    input [31:0] instruction,

    // Instruction Parts
    output [4:0] opcode,

    // Register Ports
    output [4:0] rd, rs, rt,

    // Immediate
    output [11:0] imm,

    // ALU Ports
    output use_immediate,
    output use_fpu_instruction,

    // Control Signals
    output reg reg_write_en,
    output reg mem_read,
    output reg mem_write,
    output is_branch
);
    assign opcode = instruction[31:27];
    assign rd = instruction[26:22];
    assign rs = instruction[21:17];
    assign rt = instruction[16:12];
    assign imm = instruction[11:0];

    assign use_immediate = (
        opcode == 5'h19 | // addi
        opcode == 5'h1b | // subi
        opcode == 5'h05 | // shftri
        opcode == 5'h07 | // shftli
        opcode == 5'h10 | // load
        opcode == 5'h13  // store
    );

    assign use_fpu_instruction = (
        opcode == 5'h14 |
        opcode == 5'h15 |
        opcode == 5'h16 |
        opcode == 5'h17
    );

    assign is_branch = (opcode >= 5'h08 && opcode <= 5'h0e);

    always @(*) begin
        reg_write_en = 0;
        mem_read = 0;
        mem_write = 0;

        case (opcode)
            // Math, Logic, Shifts, and Load
            5'h18, 5'h19, 5'h1a, 5'h1b, 5'h1c, 5'h1d, 
            5'h00, 5'h01, 5'h02, 5'h03,
            5'h04, 5'h05, 5'h06, 5'h07,
            5'h14, 5'h15, 5'h16, 5'h17: begin
                reg_write_en = 1;
            end
            
            5'h10, 5'h0d: begin // Load: mov rd, (rs)(L)
                mem_read = 1;
                if (opcode == 5'h10) reg_write_en = 1;
            end
            5'h13, 5'h0c: begin // Store: mov (rd)(L), rs 
                mem_write = 1;
            end
        endcase
    end
endmodule

module register_file (
    input clk,
    input reset,
    input [63:0] data,
    input [4:0] rd, rs, rt,
    input write_enable,
    output [63:0] rd_val, rs_val, rt_val,
    output [63:0] r31_val
);
    reg [63:0] registers [0:31];

    assign rd_val = registers[rd];
    assign rs_val = registers[rs];
    assign rt_val = registers[rt];
    assign r31_val = registers[31];

    integer i;

    always @(posedge clk) begin
        if (reset) begin
            for (i = 0; i < 31; i = i + 1) begin
                registers[i] <= 64'b0;
            end
            registers[31] <= 64'd524288;
        end else if (write_enable) begin
            registers[rd] <= data;
        end
    end
endmodule

module ALU (
    input [63:0] a, b,
    input [4:0] op,
    output reg [63:0] res
);
    always @(*) begin
        case (op)
            5'h00: res = a & b;
            5'h01: res = a | b;
            5'h02: res = a ^ b;
            5'h03: res = ~a;
            5'h18, 5'h19: res = a + b;
            5'h10, 5'h13: res = a + b;
            5'h1a, 5'h1b: res = a - b;
            5'h1c: res = a * b;
            5'h1d: res = a / b;
            5'h04, 5'h05: res = a >> b;
            5'h06, 5'h07: res = a << b;
            default: res = 64'b0;
        endcase
    end
endmodule

module FPU (
    input [63:0] a, b,
    input [4:0] op,
    output reg [63:0] res
);

    reg sign_a, sign_b, sign_res;
    reg [10:0] exp_a, exp_b, exp_res;
    reg [10:0] eff_exp_a, eff_exp_b; // exp for subnormals

    reg [55:0] frac_a, frac_b; // extra bit for carry + 3 GRS bits
    reg [56:0] frac_add_res; // extra bit for overflow + 3 GRS bits

    reg [52:0] m_a, m_b; // 53-bit effective fractions
    reg signed [12:0] signed_exp; // Signed to safely handle underflow/overflow
    reg [106:0] raw_mul_res; // 106 bits + 1 for rounding overflow
    reg [107:0] div_num; // Shifted numerator
    reg [56:0] raw_div_res; // 56 bits + 1 for rounding overflow

    reg[10:0] exp_diff;
    integer i;
    reg[5:0] shift_amt;
    reg[55:0] shift_mask;

    reg G, R, S, LSB;
    reg round_up;

    always @(*) begin
        res = 64'b0;

        sign_a = a[63];
        sign_b = b[63];

        exp_a = a[62:52];
        exp_b = b[62:52];
        eff_exp_a = (exp_a == 0) ? 11'd1 : exp_a;
        eff_exp_b = (exp_b == 0) ? 11'd1 : exp_b;

        frac_a = { (exp_a != 0), a[51:0], 3'b000 };
        frac_b = { (exp_b != 0), b[51:0], 3'b000 };

        case (op)
            5'h14, 5'h15: begin // addf / subf
                if (op == 5'h15) sign_b = ~sign_b;

                // Align exponents
                if (eff_exp_a > eff_exp_b) begin
                    exp_diff = eff_exp_a - eff_exp_b;
                    exp_res  = eff_exp_a;
                    if (exp_diff > 55) begin
                        frac_b = {55'b0, |frac_b};
                    end else begin
                        // shift b to the left but or the truncated bits for the sticky bit
                        shift_mask = (56'd1 << exp_diff) - 56'd1;
                        frac_b = (frac_b >> exp_diff) | {55'b0, |(frac_b & shift_mask)};
                    end
                end else if (eff_exp_b > eff_exp_a) begin
                    exp_diff = eff_exp_b - eff_exp_a;
                    exp_res  = eff_exp_b;
                    if (exp_diff > 55) begin
                        frac_a = {55'b0, |frac_a};
                    end else begin
                        shift_mask = (56'd1 << exp_diff) - 56'd1;
                        frac_a = (frac_a >> exp_diff) | {55'b0, |(frac_a & shift_mask)};
                    end
                end else begin
                    exp_res = eff_exp_a;
                end

                // Compute
                if (sign_a == sign_b) begin
                    frac_add_res = frac_a + frac_b;
                    sign_res  = sign_a;
                end else begin
                    if (frac_a >= frac_b) begin
                        frac_add_res = frac_a - frac_b;
                        sign_res  = sign_a;
                    end else begin
                        frac_add_res = frac_b - frac_a;
                        sign_res  = sign_b;
                    end
                end
                
                // Normalize
                if (frac_add_res == 0) begin
                    res = 64'b0; // Exact zero
                end else begin
                    // Check for overflow
                    if (frac_add_res[56]) begin 
                        frac_add_res = (frac_add_res >> 1) | {56'b0, frac_add_res[0]};
                        exp_res = exp_res + 1;
                    end else begin
                        // Shift left until leading 1
                        shift_amt = 0;
                        for (i = 55; i >= 0; i = i - 1) begin
                            if (frac_add_res[55] == 0 && exp_res > 0) begin
                                frac_add_res = frac_add_res << 1;
                                exp_res = exp_res - 1;
                            end
                        end
                    end

                    // Check if subnormal
                    if (exp_res == 0 && frac_add_res[55] == 1) begin
                        exp_res = 0; 
                    end

                    LSB = frac_add_res[3]; // The actual least significant bit of the 52-bit fraction
                    G = frac_add_res[2];
                    R = frac_add_res[1];
                    S = frac_add_res[0];
                    // Round up if G is 1 AND (R or S is 1 OR LSB is 1)
                    round_up = G & (R | S | LSB);
                    if (round_up) begin
                        frac_add_res = frac_add_res + 4'b1000;
                        // Check rounding overflow
                        if (frac_add_res[56]) begin
                            frac_add_res = frac_add_res >> 1;
                            exp_res = exp_res + 1;
                        end
                    end

                    // Drop implict bit
                    res = {sign_res, exp_res, frac_add_res[54:3]};
                end
            end
            5'h16: begin // mulf
                sign_res = sign_a ^ sign_b;
                m_a = { (exp_a != 0), a[51:0] };
                m_b = { (exp_b != 0), b[51:0] };

                if (m_a == 0 || m_b == 0) begin
                    res = {sign_res, 63'b0};
                end else begin
                    signed_exp = eff_exp_a + eff_exp_b - 1023;
                    raw_mul_res = m_a * m_b;
                    
                    // Normalize
                    if (raw_mul_res[105]) begin
                        signed_exp = signed_exp + 1;
                    end else begin
                        // Shift left until leading 1 is at bit 105
                        for (i = 105; i >= 0; i = i - 1) begin
                            if (raw_mul_res[105] == 0 && signed_exp > 0) begin
                                raw_mul_res = raw_mul_res << 1;
                                signed_exp = signed_exp - 1;
                            end
                        end
                    end

                    // GRS rounding
                    LSB = raw_mul_res[53];
                    G = raw_mul_res[52];
                    R = raw_mul_res[51];
                    S = |raw_mul_res[50:0];
                    round_up = G & (R | S | LSB);

                    if (round_up) begin
                        raw_mul_res = raw_mul_res + (107'b1 << 53);
                        if (raw_mul_res[106]) begin // Rounding overflow
                            raw_mul_res = raw_mul_res >> 1;
                            signed_exp = signed_exp + 1;
                        end
                    end

                    // Cap exponents
                    if (signed_exp <= 0) exp_res = 0; // Subnormal
                    else if (signed_exp >= 2047) exp_res = 11'h7FF; // Infinity
                    else exp_res = signed_exp[10:0];

                    res = {sign_res, exp_res, raw_mul_res[104:53]};
                end
            end
            5'h17: begin // divf
                sign_res = sign_a ^ sign_b;
                m_a = { (exp_a != 0), a[51:0] };
                m_b = { (exp_b != 0), b[51:0] };

                if (m_b == 0) begin
                    res = {sign_res, 11'h7FF, 52'b0}; // Div by zero -> Infinity
                end else if (m_a == 0) begin
                    res = {sign_res, 63'b0}; // 0 / X -> 0
                end else begin
                    signed_exp = eff_exp_a - eff_exp_b + 1023;
                    
                    // Shift numerator left by 55 bits to generate 56 bits of quotient
                    div_num = {m_a, 55'b0};
                    raw_div_res = div_num / m_b;
                    
                    // Normalize the quotient
                    if (raw_div_res[55]) begin
                        // Already proper form 1....
                    end else begin
                        for (i = 55; i >= 0; i = i - 1) begin
                            if (raw_div_res[55] == 0 && signed_exp > 0) begin
                                raw_div_res = raw_div_res << 1;
                                signed_exp = signed_exp - 1;
                            end
                        end
                    end

                    // GRS rounding
                    LSB = raw_div_res[3];
                    G = raw_div_res[2];
                    R = raw_div_res[1];
                    S = |(div_num % m_b) | raw_div_res[0]; 
                    
                    round_up = G & (R | S | LSB);

                    if (round_up) begin
                        raw_div_res = raw_div_res + 4'b1000;
                        if (raw_div_res[56]) begin // Rounding overflow
                            raw_div_res = raw_div_res >> 1;
                            signed_exp = signed_exp + 1;
                        end
                    end

                    // Cap exponents
                    if (signed_exp <= 0) exp_res = 0; 
                    else if (signed_exp >= 2047) exp_res = 11'h7FF; 
                    else exp_res = signed_exp[10:0];

                    res = {sign_res, exp_res, raw_div_res[54:3]};
                end
            end
            default: res = 64'b0;
        endcase
    end
endmodule

module instruction_fetch_unit (
    input clk,
    input reset,
    input [63:0] branch_target,
    input take_branch,
    output reg [63:0] pc
);
    always @(posedge clk) begin
        if (reset) begin
            pc <= 64'h2000;
        end else if (take_branch) begin
            pc <= branch_target;
        end else begin
            pc <= pc + 4;
        end
    end
endmodule

module memory (
    input clk,
    input [63:0] addr,
    input [63:0] write_data,
    input mem_write,
    input mem_read,
    output [63:0] read_data
);
    parameter MEM_SIZE = 524288;
    reg [7:0] bytes [0:MEM_SIZE - 1];

    assign read_data = mem_read ? {
        bytes[addr + 7], bytes[addr + 6], bytes[addr + 5], bytes[addr + 4], 
        bytes[addr + 3], bytes[addr + 2], bytes[addr + 1], bytes[addr]
    } : 64'b0;

    always @(posedge clk) begin
        if (mem_write) begin
            bytes[addr] <= write_data[7:0];
            bytes[addr+1] <= write_data[15:8];
            bytes[addr+2] <= write_data[23:16];
            bytes[addr+3] <= write_data[31:24];
            bytes[addr+4] <= write_data[39:32];
            bytes[addr+5] <= write_data[47:40];
            bytes[addr+6] <= write_data[55:48];
            bytes[addr+7] <= write_data[63:56];
        end
    end 
endmodule

module tinker_core (
    input clk,
    input reset
);
    wire [63:0] pc;
    wire [31:0] current_instruction;

    wire [4:0] opcode, rd, rs, rt;
    wire [11:0] imm;
    wire use_immediate, use_fpu_instruction;
    wire reg_write_en, mem_read, mem_write;

    wire [63:0] rd_val, rs_val, rt_val, alu_res, fpu_res;
    wire [63:0] alu_input_a, alu_input_b;
    wire [63:0] reg_write_data, mem_read_data;

    wire is_branch;
    reg take_branch;
    reg [63:0] branch_target;

    wire [63:0] r31_val;

    instruction_fetch_unit fetch (
        .clk(clk), 
        .reset(reset),
        .branch_target(branch_target),
        .take_branch(take_branch),
        .pc(pc)
    );

    assign current_instruction = {
        memory.bytes[pc+3], memory.bytes[pc+2], 
        memory.bytes[pc+1], memory.bytes[pc]
    };

    instruction_decoder decoder (
        .instruction(current_instruction),
        .opcode(opcode), 
        .rd(rd), .rs(rs), .rt(rt),
        .imm(imm),
        .use_immediate(use_immediate),
        .use_fpu_instruction(use_fpu_instruction),
        .reg_write_en(reg_write_en),
        .mem_read(mem_read),
        .mem_write(mem_write),
        .is_branch(is_branch)
    );

    register_file reg_file (
        .clk(clk),
        .reset(reset),
        .data(reg_write_data),
        .rd(rd), .rs(rs), .rt(rt),
        .write_enable(reg_write_en),
        .rd_val(rd_val), .rs_val(rs_val), .rt_val(rt_val),
        .r31_val(r31_val)
    );

    assign alu_input_b = (use_immediate) ? {{52{imm[11]}}, imm} : rt_val;
    assign alu_input_a = (opcode == 5'h13) ? rd_val : rs_val;

    ALU alu (.a(alu_input_a), .b(alu_input_b), .op(opcode), .res(alu_res));
    FPU fpu (.a(rs_val), .b(alu_input_b), .op(opcode), .res(fpu_res));

    wire [63:0] stack_addr = r31_val - 8;
    wire [63:0] mem_addr = (opcode == 5'h0c || opcode == 5'h0d) ? stack_addr : alu_res;
    wire [63:0] mem_wdata = (opcode == 5'h0c) ? (pc + 4) : rs_val;

    memory memory (
        .clk(clk), .addr(mem_addr), 
        .write_data(mem_wdata), 
        .mem_write(mem_write),
        .mem_read(mem_read),
        .read_data(mem_read_data)
    );

    assign reg_write_data = (use_fpu_instruction) ? fpu_res : (mem_read) ? mem_read_data : alu_res;

    // Signed casts for the brgt comparison
    wire signed [63:0] signed_rs = rs_val;
    wire signed [63:0] signed_rt = rt_val;

    always @(*) begin
        take_branch = 1'b0;
        branch_target = 64'b0;

        if (is_branch) begin
            case (opcode)
                5'h08: begin // br rd
                    take_branch = 1'b1;
                    branch_target = rd_val;
                end
                5'h09: begin // brr rd
                    take_branch = 1'b1;
                    branch_target = pc + rd_val;
                end
                5'h0a: begin // brr L
                    take_branch = 1'b1;
                    branch_target = pc + {{52{imm[11]}}, imm}; 
                end
                5'h0b: begin // brnz rd, rs
                    if (rs_val != 0) begin
                        take_branch = 1'b1;
                        branch_target = rd_val;
                    end
                end
                5'h0c: begin // call
                    take_branch = 1'b1;
                    branch_target = rd_val;
                end
                5'h0d: begin // return
                    take_branch = 1'b1;
                    branch_target = mem_read_data;
                end
                5'h0e: begin // brgt rd, rs, rt
                    if (signed_rs > signed_rt) begin
                        take_branch = 1'b1;
                        branch_target = rd_val;
                    end
                end
            endcase
        end
    end

    // testing halt mechanic
    always @(posedge clk) begin
        if (opcode == 5'h0f && imm == 12'b0) begin
            $display("Execution Halted.");
            $finish; 
        end
    end
endmodule

tb_tinker.sv
`timescale 1ns / 1ps

module tb_tinker;
    // Core Inputs
    reg clk;
    reg reset;

    // Instantiate the Unit Under Test (UUT)
    tinker_core uut (.clk(clk), .reset(reset));

    // Clock Generation: toggles every 5 nanoseconds
    always #5 clk = ~clk;

    // Little endian write instruction and write memory
    task write_inst;
        input [63:0] addr;
        input [31:0] inst;
        begin
            uut.memory.bytes[addr]   = inst[7:0];
            uut.memory.bytes[addr+1] = inst[15:8];
            uut.memory.bytes[addr+2] = inst[23:16];
            uut.memory.bytes[addr+3] = inst[31:24];
        end
    endtask

    task write_mem64;
        input [63:0] addr;
        input [63:0] data;
        begin
            uut.memory.bytes[addr]   = data[7:0];
            uut.memory.bytes[addr+1] = data[15:8];
            uut.memory.bytes[addr+2] = data[23:16];
            uut.memory.bytes[addr+3] = data[31:24];
            uut.memory.bytes[addr+4] = data[39:32];
            uut.memory.bytes[addr+5] = data[47:40];
            uut.memory.bytes[addr+6] = data[55:48];
            uut.memory.bytes[addr+7] = data[63:56];
        end
    endtask

    initial begin
        $dumpfile("tinker_waves.vcd");
        $dumpvars(0, tb_tinker);
        
        clk = 0;
        reset = 1;

        // Load the IEEE-754 double precision value for 1.5 at address 0x108
        write_mem64(64'h0108, 64'h3FF8000000000000);

        // 0x2000: addi r1, 15
        write_inst(64'h2000, 32'hC840000F); 
        // 0x2004: addi r2, 5
        write_inst(64'h2004, 32'hC8800005); 
        // 0x2008: add r3, r1, r2    (r3 should become 15 + 5 = 20)
        write_inst(64'h2008, 32'hC0C22000); 
        // 0x200C: sub r4, r1, r2    (r4 should become 15 - 5 = 10)
        write_inst(64'h200C, 32'hD1022000); 
        // 0x2010: mul r5, r1, r2    (r5 should become 15 * 5 = 75)
        write_inst(64'h2010, 32'hE1422000); 
        // 0x2014: div r6, r1, r2    (r6 should become 15 / 5 = 3)
        write_inst(64'h2014, 32'hE9822000); 

        // 0x2018: xor r7, r1, r2    (15 XOR 5 = 10)
        write_inst(64'h2018, 32'h11C22000); 
        // 0x201C: shftli r8, r1, 2  (Shift r1 left by 2: 15 << 2 = 60)
        write_inst(64'h201C, 32'h3A020002); 
        
        // 0x2020: mov (r0)(0x100), r8  (Store the 60 from r8 into memory at 0x100)
        write_inst(64'h2020, 32'h98100100); 
        // 0x2024: mov r9, (r0)(0x100)  (Load that 60 back out into r9)
        write_inst(64'h2024, 32'h82400100); 
        
        // 0x2028: brr 8                (Jump forward 8 bytes -> PC moves to 0x2030)
        write_inst(64'h2028, 32'h50000008); 
        // 0x202C: addi r0, 999         (THIS SHOULD BE SKIPPED!)
        write_inst(64'h202C, 32'hC80003E7); 
        
        // 0x2030: mov r11, (r0)(0x108) (Load the double 1.5 from memory 0x108)
        write_inst(64'h2030, 32'h82C00108); 
        // 0x2034: addf r12, r11, r11   (1.5 + 1.5 = 3.0. r12 should equal 0x4008000000000000)
        write_inst(64'h2034, 32'hA316B000); 

        // 0x2038: priv 0               (Triggers the Halt command)
        write_inst(64'h2038, 32'h78000000); 

        // Release reset and let the CPU run
        #15 reset = 0;

        // Failsafe timeout
        #500;
        $display("\n[ERROR] Timeout! The CPU did not hit the Halt instruction.");
        $finish;
    end

    // This will print to the console every time a monitored register changes!
    initial begin
        $monitor("Time=%0t | PC=%h | r3(Add)=%0d | r8(Shft)=%0d | r9(Mem)=%0d | r12(FPU)=%h", 
                 $time, uut.pc, 
                 uut.reg_file.registers[3], 
                 uut.reg_file.registers[8], 
                 uut.reg_file.registers[9],
                 uut.reg_file.registers[12]);
    end

endmodule

tinker_waves.vcd
$date
	Wed Mar 25 15:39:23 2026
$end
$version
	Icarus Verilog
$end
$timescale
	1ps
$end
$scope module tb_tinker $end
$var reg 1 ! clk $end
$var reg 1 " reset $end
$scope module uut $end
$var wire 1 ! clk $end
$var wire 64 # r31_val [63:0] $end
$var wire 1 " reset $end
$var wire 64 $ signed_rs [63:0] $end
$var wire 64 % signed_rt [63:0] $end
$var wire 1 & use_immediate $end
$var wire 1 ' use_fpu_instruction $end
$var wire 64 ( stack_addr [63:0] $end
$var wire 64 ) rt_val [63:0] $end
$var wire 5 * rt [4:0] $end
$var wire 64 + rs_val [63:0] $end
$var wire 5 , rs [4:0] $end
$var wire 1 - reg_write_en $end
$var wire 64 . reg_write_data [63:0] $end
$var wire 64 / rd_val [63:0] $end
$var wire 5 0 rd [4:0] $end
$var wire 64 1 pc [63:0] $end
$var wire 5 2 opcode [4:0] $end
$var wire 1 3 mem_write $end
$var wire 64 4 mem_wdata [63:0] $end
$var wire 64 5 mem_read_data [63:0] $end
$var wire 1 6 mem_read $end
$var wire 64 7 mem_addr [63:0] $end
$var wire 1 8 is_branch $end
$var wire 12 9 imm [11:0] $end
$var wire 64 : fpu_res [63:0] $end
$var wire 32 ; current_instruction [31:0] $end
$var wire 64 < alu_res [63:0] $end
$var wire 64 = alu_input_b [63:0] $end
$var wire 64 > alu_input_a [63:0] $end
$var reg 64 ? branch_target [63:0] $end
$var reg 1 @ take_branch $end
$scope module alu $end
$var wire 64 A a [63:0] $end
$var wire 64 B b [63:0] $end
$var wire 5 C op [4:0] $end
$var reg 64 D res [63:0] $end
$upscope $end
$scope module decoder $end
$var wire 32 E instruction [31:0] $end
$var wire 1 8 is_branch $end
$var wire 1 ' use_fpu_instruction $end
$var wire 1 & use_immediate $end
$var wire 5 F rt [4:0] $end
$var wire 5 G rs [4:0] $end
$var wire 5 H rd [4:0] $end
$var wire 5 I opcode [4:0] $end
$var wire 12 J imm [11:0] $end
$var reg 1 6 mem_read $end
$var reg 1 3 mem_write $end
$var reg 1 - reg_write_en $end
$upscope $end
$scope module fetch $end
$var wire 64 K branch_target [63:0] $end
$var wire 1 ! clk $end
$var wire 1 " reset $end
$var wire 1 @ take_branch $end
$var reg 64 L pc [63:0] $end
$upscope $end
$scope module fpu $end
$var wire 64 M b [63:0] $end
$var wire 5 N op [4:0] $end
$var wire 64 O a [63:0] $end
$var reg 1 P G $end
$var reg 1 Q LSB $end
$var reg 1 R R $end
$var reg 1 S S $end
$var reg 108 T div_num [107:0] $end
$var reg 11 U eff_exp_a [10:0] $end
$var reg 11 V eff_exp_b [10:0] $end
$var reg 11 W exp_a [10:0] $end
$var reg 11 X exp_b [10:0] $end
$var reg 11 Y exp_diff [10:0] $end
$var reg 11 Z exp_res [10:0] $end
$var reg 56 [ frac_a [55:0] $end
$var reg 57 \ frac_add_res [56:0] $end
$var reg 56 ] frac_b [55:0] $end
$var reg 53 ^ m_a [52:0] $end
$var reg 53 _ m_b [52:0] $end
$var reg 57 ` raw_div_res [56:0] $end
$var reg 107 a raw_mul_res [106:0] $end
$var reg 64 b res [63:0] $end
$var reg 1 c round_up $end
$var reg 6 d shift_amt [5:0] $end
$var reg 56 e shift_mask [55:0] $end
$var reg 1 f sign_a $end
$var reg 1 g sign_b $end
$var reg 1 h sign_res $end
$var reg 13 i signed_exp [12:0] $end
$var integer 32 j i [31:0] $end
$upscope $end
$scope module memory $end
$var wire 64 k addr [63:0] $end
$var wire 1 ! clk $end
$var wire 1 6 mem_read $end
$var wire 1 3 mem_write $end
$var wire 64 l write_data [63:0] $end
$var wire 64 m read_data [63:0] $end
$var parameter 32 n MEM_SIZE $end
$upscope $end
$scope module reg_file $end
$var wire 1 ! clk $end
$var wire 64 o data [63:0] $end
$var wire 64 p r31_val [63:0] $end
$var wire 5 q rd [4:0] $end
$var wire 64 r rd_val [63:0] $end
$var wire 1 " reset $end
$var wire 5 s rs [4:0] $end
$var wire 64 t rs_val [63:0] $end
$var wire 5 u rt [4:0] $end
$var wire 64 v rt_val [63:0] $end
$var wire 1 - write_enable $end
$var integer 32 w i [31:0] $end
$upscope $end
$upscope $end
$scope task write_inst $end
$var reg 64 x addr [63:0] $end
$var reg 32 y inst [31:0] $end
$upscope $end
$scope task write_mem64 $end
$var reg 64 z addr [63:0] $end
$var reg 64 { data [63:0] $end
$upscope $end
$upscope $end
$enddefinitions $end
$comment Show the parameter values. $end
$dumpall
b10000000000000000000 n
$end
#0
$dumpvars
b11111111111000000000000000000000000000000000000000000000000000 {
b100001000 z
b1111000000000000000000000000000 y
b10000000111000 x
bx w
bx v
bx u
bx t
bx s
bx r
bx q
bx p
bx o
bx m
bx l
bx k
bx j
bx i
xh
xg
xf
bx e
bx d
xc
bx b
bx a
bx `
bx _
bx ^
bx ]
bx \
bx [
bx Z
bx Y
bx X
bx W
bx V
bx U
bx T
xS
xR
xQ
xP
bx O
bx N
bx M
bx L
bx K
bx J
bx I
bx H
bx G
bx F
bx E
bx D
bx C
bx B
bx A
x@
bx ?
bx >
bx =
bx <
bx ;
bx :
bx 9
x8
bx 7
x6
bx 5
bx 4
x3
bx 2
bx 1
bx 0
bx /
bx .
x-
bx ,
bx +
bx *
bx )
bx (
x'
x&
bx %
bx $
bx #
1"
0!
$end
#5000
b1111 .
b1111 o
b1111 7
b1111 k
b1111 <
b1111 D
1&
b1 V
b0 X
0g
0'
b0 5
b0 m
b1111 =
b1111 B
b1111 M
08
03
06
1-
b1111000 ]
b0 [
b1 U
b0 W
0f
b0 :
b0 b
b0 >
b0 A
b0 4
b0 l
b1111 9
b1111 J
b0 $
b0 +
b0 O
b0 t
b0 ,
b0 G
b0 s
b0 %
b0 )
b0 v
b0 *
b0 F
b0 u
b11001 2
b11001 C
b11001 I
b11001 N
b0 /
b0 r
b1 0
b1 H
b1 q
b0 ?
b0 K
0@
b11001000010000000000000000001111 ;
b11001000010000000000000000001111 E
b10000000000000 1
b10000000000000 L
b1111111111111111000 (
b10000000000000000000 #
b10000000000000000000 p
b11111 w
1!
#10000
0!
#15000
b101 .
b101 o
b101 7
b101 k
b101 <
b101 D
b101000 ]
b101 =
b101 B
b101 M
b101 9
b101 J
b10 0
b10 H
b10 q
b0 /
b0 r
b11001000100000000000000000000101 ;
b11001000100000000000000000000101 E
b10000000000100 1
b10000000000100 L
1!
0"
#20000
0!
#25000
0&
b10100 .
b10100 o
b10100 7
b10100 k
b101000 ]
b10100 <
b10100 D
b101 =
b101 B
b101 M
b1111 4
b1111 l
b1111 >
b1111 A
1-
b1111000 [
b0 9
b0 J
b101 %
b101 )
b101 v
b10 *
b10 F
b10 u
b11 0
b11 H
b11 q
b1111 $
b1111 +
b1111 O
b1111 t
b1 ,
b1 G
b1 s
b11000 2
b11000 C
b11000 I
b11000 N
b11000000110000100010000000000000 ;
b11000000110000100010000000000000 E
b10000000001000 1
b10000000001000 L
b0 /
b0 r
1!
#30000
0!
#35000
b1010 .
b1010 o
b1010 7
b1010 k
b1010 <
b1010 D
1-
b11010 2
b11010 C
b11010 I
b11010 N
b100 0
b100 H
b100 q
b0 /
b0 r
b11010001000000100010000000000000 ;
b11010001000000100010000000000000 E
b10000000001100 1
b10000000001100 L
1!
#40000
0!
#45000
b1001011 .
b1001011 o
b1001011 7
b1001011 k
b1001011 <
b1001011 D
1-
b101 0
b101 H
b101 q
b11100 2
b11100 C
b11100 I
b11100 N
b11100001010000100010000000000000 ;
b11100001010000100010000000000000 E
b10000000010000 1
b10000000010000 L
b0 /
b0 r
1!
#50000
0!
#55000
b11 .
b11 o
b11 7
b11 k
b11 <
b11 D
1-
b110 0
b110 H
b110 q
b11101 2
b11101 C
b11101 I
b11101 N
b0 /
b0 r
b11101001100000100010000000000000 ;
b11101001100000100010000000000000 E
b10000000010100 1
b10000000010100 L
1!
#60000
0!
#65000
b1010 .
b1010 o
b1010 7
b1010 k
b1010 <
b1010 D
1-
b111 0
b111 H
b111 q
b10 2
b10 C
b10 I
b10 N
b10001110000100010000000000000 ;
b10001110000100010000000000000 E
b10000000011000 1
b10000000011000 L
b0 /
b0 r
1!
#70000
0!
#75000
1&
b111100 .
b111100 o
b10000 ]
b111100 7
b111100 k
b10 =
b10 B
b10 M
b111100 <
b111100 D
1-
b10 9
b10 J
b0 %
b0 )
b0 v
b0 *
b0 F
b0 u
b111 2
b111 C
b111 I
b111 N
b1000 0
b1000 H
b1000 q
b0 /
b0 r
b111010000000100000000000000010 ;
b111010000000100000000000000010 E
b10000000011100 1
b10000000011100 L
1!
#80000
0!
#85000
b100000000 .
b100000000 o
b100000000000 ]
b100000000 7
b100000000 k
b100000000 =
b100000000 B
b100000000 M
b111100 4
b111100 l
b0 >
b0 A
b100000000 <
b100000000 D
13
0-
b111100000 [
b100000000 9
b100000000 J
b111100 $
b111100 +
b111100 O
b111100 t
b1000 ,
b1000 G
b1000 s
b10011 2
b10011 C
b10011 I
b10011 N
b0 0
b0 H
b0 q
b10011000000100000000000100000000 ;
b10011000000100000000000100000000 E
b10000000100000 1
b10000000100000 L
b0 /
b0 r
1!
#90000
0!
#95000
b100000000 7
b100000000 k
b100000000 <
b100000000 D
b100000000000 ]
b111100 .
b111100 o
b100000000 =
b100000000 B
b100000000 M
b111100 5
b111100 m
b0 4
b0 l
1&
1-
16
03
b0 [
b0 $
b0 +
b0 O
b0 t
b0 ,
b0 G
b0 s
b10000 2
b10000 C
b10000 I
b10000 N
b1001 0
b1001 H
b1001 q
b10000010010000000000000100000000 ;
b10000010010000000000000100000000 E
b10000000100100 1
b10000000100100 L
1!
#100000
0!
#105000
b0 .
b0 o
b0 ]
0&
b10000000110000 ?
b10000000110000 K
1@
b0 7
b0 k
b0 5
b0 m
b0 =
b0 B
b0 M
18
b0 <
b0 D
06
0-
b1000 9
b1000 J
b1010 2
b1010 C
b1010 I
b1010 N
b0 0
b0 H
b0 q
b1010000000000000000000000001000 ;
b1010000000000000000000000001000 E
b10000000101000 1
b10000000101000 L
b0 /
b0 r
1!
#110000
0!
#115000
b100001000 7
b100001000 k
b100001000 <
b100001000 D
b100001000000 ]
b11111111111000000000000000000000000000000000000000000000000000 .
b11111111111000000000000000000000000000000000000000000000000000 o
b100001000 =
b100001000 B
b100001000 M
1&
b11111111111000000000000000000000000000000000000000000000000000 5
b11111111111000000000000000000000000000000000000000000000000000 m
08
1-
16
b100001000 9
b100001000 J
b10000 2
b10000 C
b10000 I
b10000 N
b1011 0
b1011 H
b1011 q
b0 ?
b0 K
0@
b10000010110000000000000100001000 ;
b10000010110000000000000100001000 E
b10000000110000 1
b10000000110000 L
1!
#120000
0!
#125000
b1111111111 V
b1111111111 X
1'
b100000000001000000000000000000000000000000000000000000000000000 .
b100000000001000000000000000000000000000000000000000000000000000 o
0&
b0 7
b0 k
b0 5
b0 m
b11111111111000000000000000000000000000000000000000000000000000 =
b11111111111000000000000000000000000000000000000000000000000000 B
b11111111111000000000000000000000000000000000000000000000000000 M
b11111111111000000000000000000000000000000000000000000000000000 4
b11111111111000000000000000000000000000000000000000000000000000 l
b11111111111000000000000000000000000000000000000000000000000000 >
b11111111111000000000000000000000000000000000000000000000000000 A
b0 <
b0 D
06
1-
b100000000001000000000000000000000000000000000000000000000000000 :
b100000000001000000000000000000000000000000000000000000000000000 b
0c
0S
0R
0P
0Q
b11111111111111111111111111111111 j
b0 d
0h
b11000000000000000000000000000000000000000000000000000000 \
b11000000000000000000000000000000000000000000000000000000 ]
b10000000000 Z
b1111111110 Y
b11000000000000000000000000000000000000000000000000000000 [
b1111111111 U
b1111111111 W
b11111111111000000000000000000000000000000000000000000000000000 %
b11111111111000000000000000000000000000000000000000000000000000 )
b11111111111000000000000000000000000000000000000000000000000000 v
b1011 *
b1011 F
b1011 u
b0 9
b0 J
b11111111111000000000000000000000000000000000000000000000000000 $
b11111111111000000000000000000000000000000000000000000000000000 +
b11111111111000000000000000000000000000000000000000000000000000 O
b11111111111000000000000000000000000000000000000000000000000000 t
b1011 ,
b1011 G
b1011 s
b10100 2
b10100 C
b10100 I
b10100 N
b1100 0
b1100 H
b1100 q
b10100011000101101011000000000000 ;
b10100011000101101011000000000000 E
b10000000110100 1
b10000000110100 L
b0 /
b0 r
1!
#130000
0!
